{
  "id": "chupacabra",
  "name": "Chupacabra",
  "formerNames": [
    "Gambit at Thrill Valley  Batman: The Ride at Six Flags New Orleans  Goliath at Six Flags Fiesta Texas"
  ],
  "parkId": "six-flags-fiesta-texas",
  "parkName": "Six Flags Fiesta Texas",
  "country": "US",
  "countryName": "United States",
  "region": "Texas",
  "continent": "North America",
  "heightFt": 105,
  "heightM": 32,
  "speedMph": 50,
  "speedKmh": 80.5,
  "lengthFt": 2693,
  "lengthM": 820.8,
  "dropFt": 80,
  "dropM": 24.4,
  "inversions": 5,
  "gForce": 4,
  "duration": 120,
  "material": "Steel",
  "type": "Inverted",
  "propulsion": "Chain lift",
  "manufacturer": "Bolliger & Mabillard",
  "designer": "Werner Stengel",
  "model": "Inverted Coaster - Batman",
  "status": "operating",
  "yearOpened": 2008,
  "yearClosed": null,
  "description": "Chupacabra is an inverted roller coaster at Six Flags Fiesta Texas in San Antonio, Texas, United States.  Designed by Werner Stengel and Swiss manufacturer Bolliger & Mabillard, Chupacabra initially opened in Japan in 1995 at Odakyu Gotemba Family Land, later known as Thrill Valley.  In 2002, it was moved to Six Flags New Orleans where it reopened as Batman: The Ride the following year, operating until Hurricane Katrina led to the park's abandonment in 2005.",
  "history": null,
  "notableFeatures": [],
  "records": [],
  "imageUrl": "https://en.wikipedia.org/wiki/Special:FilePath/Goliath_Fiesta_Texas.jpg",
  "imageAttribution": null,
  "wikiUrl": "https://en.wikipedia.org/wiki/Chupacabra_(roller_coaster)",
  "dataSource": [
    "wikipedia",
    "coasterpedia"
  ],
  "lastUpdated": "2026-02-28T21:37:45.000Z",
  "dataQuality": "verified",
  "searchTerms": [
    "chupacabra",
    "gambit at thrill valley  batman: the ride at six flags new orleans  goliath at six flags fiesta texas",
    "six flags fiesta texas",
    "bolliger & mabillard",
    "b&m",
    "inverted coaster - batman",
    "inverted",
    "texas"
  ],
  "_meta": {
    "manufacturerMatched": true,
    "manufacturerRaw": "Bolliger & Mabillard"
  },
  "coasterpedia": {
    "url": "https://coasterpedia.net/wiki/Chupacabra_(Six_Flags_Fiesta_Texas)",
    "minRiderHeight": 54,
    "minUnaccompaniedHeight": null,
    "maxRiderHeight": null,
    "ridersPerTrain": 28,
    "ridersPerHour": null,
    "section": null,
    "subsection": null,
    "steepestDrop": null,
    "cost": null,
    "theme": null,
    "soundtrack": null,
    "serialNumber": null,
    "trainManufacturer": null,
    "trackInversions": null,
    "riderInversions": null,
    "categories": [
      "Steel",
      "Inverted"
    ],
    "product": "Inverted Coaster (Batman)",
    "layout": null,
    "bankAngle": null,
    "builder": null,
    "gForce": null,
    "replaced": null,
    "replacement": null,
    "fetchedAt": "2026-02-28T21:37:44.998Z"
  },
  "popularityScore": 68.5,
  "popularityTier": "iconic",
  "popularityRank": 235
}