{
  "source": "coasterpedia",
  "articleTitle": "Circuit Breaker",
  "introSection": "Circuit Breaker is a steel roller coaster built by Dutch manufacturer Vekoma at Cotaland in Austin, Texas, USA.",
  "sections": [
    {
      "title": "History",
      "content": "The addition of Circuit Breaker was announced in spring 2022. Circuit Breaker opened on October 17, 2025."
    },
    {
      "title": "Trains",
      "content": "5 cars per train. Riders are arranged 2 across in 2 rows for a total of 20 riders per train."
    }
  ],
  "fullText": "Circuit Breaker is a steel roller coaster built by Dutch manufacturer Vekoma at Cotaland in Austin, Texas, USA.\n\nThe addition of Circuit Breaker was announced in spring 2022. Circuit Breaker opened on October 17, 2025.\n\n\n\n5 cars per train. Riders are arranged 2 across in 2 rows for a total of 20 riders per train.\n\n",
  "categories": [
    "Pages_with_short_description",
    "Pages_using_Details_parser_tag",
    "Roller_coasters_by_name",
    "Operating_roller_coasters",
    "Roller_coasters_in_Texas",
    "Steel_roller_coasters",
    "Pages_with_park_navbox",
    "Roller_coasters_manufactured_by_Vekoma",
    "Roller_coasters_opened_in_2026",
    "Tilt_Coaster_(Vekoma)"
  ],
  "url": "https://coasterpedia.net/wiki/Circuit_Breaker",
  "pageId": 45605,
  "fetchedAt": "2026-02-28T21:37:52.766Z",
  "articleLength": 316
}