{
  "id": "figure-eight-euclid-beach-park",
  "name": "Figure Eight",
  "formerNames": [],
  "parkId": "euclid-beach-park",
  "parkName": "Euclid Beach Park",
  "country": "US",
  "countryName": "United States",
  "region": "Ohio",
  "continent": "North America",
  "heightFt": null,
  "heightM": null,
  "speedMph": null,
  "speedKmh": null,
  "lengthFt": null,
  "lengthM": null,
  "dropFt": null,
  "dropM": null,
  "inversions": 0,
  "gForce": null,
  "duration": null,
  "material": "Wood",
  "type": "Sit-down",
  "propulsion": null,
  "manufacturer": "Philadelphia Toboggan Coasters",
  "designer": "Henry B. Auchy",
  "model": null,
  "status": "closed",
  "yearOpened": 1904,
  "yearClosed": 1909,
  "description": "Figure Eight was a wooden roller coaster previously located at Euclid Beach Park in Cleveland, Ohio, USA.",
  "history": null,
  "notableFeatures": [],
  "records": [],
  "imageUrl": null,
  "imageAttribution": null,
  "wikiUrl": null,
  "coasterpedia": {
    "url": "https://coasterpedia.net/wiki/Figure_Eight_(Euclid_Beach_Park)",
    "minRiderHeight": null,
    "minUnaccompaniedHeight": null,
    "maxRiderHeight": null,
    "ridersPerTrain": null,
    "ridersPerHour": null,
    "section": null,
    "subsection": null,
    "steepestDrop": null,
    "cost": null,
    "theme": null,
    "soundtrack": null,
    "serialNumber": null,
    "trainManufacturer": null,
    "trackInversions": null,
    "riderInversions": null,
    "categories": [
      "Wooden"
    ],
    "product": null,
    "layout": null,
    "bankAngle": null,
    "builder": null,
    "gForce": null,
    "replaced": "Switchback Railway",
    "replacement": "Aero Dips",
    "fetchedAt": "2026-02-28T21:49:26.426Z"
  },
  "dataSource": [
    "coasterpedia"
  ],
  "lastUpdated": "2026-02-28T21:49:26.428Z",
  "dataQuality": "stub",
  "searchTerms": [
    "figure eight",
    "euclid beach park",
    "philadelphia toboggan coasters",
    "ptc",
    "sit-down",
    "ohio"
  ],
  "_meta": {
    "manufacturerMatched": true,
    "manufacturerRaw": "Philadelphia Toboggan Company"
  },
  "popularityScore": 3.6,
  "popularityTier": "standard",
  "popularityRank": 2592
}