{
  "id": "galaxi-joyland-amusement-park",
  "name": "Galaxi",
  "formerNames": [],
  "parkId": "joyland-amusement-park",
  "parkName": "Joyland Amusement Park",
  "country": "US",
  "countryName": "United States",
  "region": "Texas",
  "continent": "North America",
  "heightFt": null,
  "heightM": null,
  "speedMph": null,
  "speedKmh": null,
  "lengthFt": null,
  "lengthM": null,
  "dropFt": null,
  "dropM": null,
  "inversions": 0,
  "gForce": null,
  "duration": null,
  "material": "Steel",
  "type": "Sit-down",
  "propulsion": null,
  "manufacturer": "SDC",
  "designer": null,
  "model": "Galaxi (large)",
  "status": "closed",
  "yearOpened": 1991,
  "yearClosed": 2022,
  "description": "Galaxi was a steel roller coaster previously located at Joyland Amusement Park in Lubbock, Texas, USA.  The attraction previously operated at White Swan Park from 1972 until the closure of the park in 1989.  It sat standing but not operating for most of 1990 before reopening at Joyland in 1991.",
  "history": null,
  "notableFeatures": [],
  "records": [],
  "imageUrl": null,
  "imageAttribution": null,
  "wikiUrl": null,
  "coasterpedia": {
    "url": "https://coasterpedia.net/wiki/Galaxi_(Joyland_Amusement_Park)",
    "minRiderHeight": 42,
    "minUnaccompaniedHeight": null,
    "maxRiderHeight": null,
    "ridersPerTrain": 8,
    "ridersPerHour": null,
    "section": null,
    "subsection": null,
    "steepestDrop": null,
    "cost": null,
    "theme": null,
    "soundtrack": null,
    "serialNumber": null,
    "trainManufacturer": null,
    "trackInversions": null,
    "riderInversions": null,
    "categories": [
      "Steel"
    ],
    "product": "Galaxi (large)",
    "layout": "zyklon/galaxi",
    "bankAngle": null,
    "builder": null,
    "gForce": null,
    "replaced": null,
    "replacement": null,
    "fetchedAt": "2026-02-28T21:52:58.095Z"
  },
  "dataSource": [
    "coasterpedia"
  ],
  "lastUpdated": "2026-02-28T21:52:58.096Z",
  "dataQuality": "stub",
  "searchTerms": [
    "galaxi",
    "joyland amusement park",
    "sdc",
    "galaxi (large)",
    "sit-down",
    "texas"
  ],
  "_meta": {
    "manufacturerMatched": false,
    "manufacturerRaw": "SDC"
  },
  "popularityScore": 3.5,
  "popularityTier": "standard",
  "popularityRank": 2632
}