{
  "source": "coasterpedia",
  "articleTitle": "Jack Rabbit",
  "introSection": "Jack Rabbit was a wooden roller coaster previously located at Riverview Park in Chicago, Illinois, USA.",
  "sections": [],
  "fullText": "Jack Rabbit was a wooden roller coaster previously located at Riverview Park in Chicago, Illinois, USA.\n\n\n\n",
  "categories": [
    "Pages_with_short_description",
    "Pages_using_Details_parser_tag",
    "Infoboxes_using_placeholder_image",
    "Roller_coasters_by_name",
    "Defunct_roller_coasters",
    "Roller_coasters_in_Illinois",
    "Wooden_roller_coasters",
    "Pages_with_park_navbox",
    "Roller_coasters_opened_in_1914",
    "Roller_coasters_closed_in_1932"
  ],
  "url": "https://coasterpedia.net/wiki/Jack_Rabbit_(Riverview_Park)",
  "pageId": 63174,
  "fetchedAt": "2026-02-28T22:00:13.101Z",
  "articleLength": 107
}