{
  "id": "loop-the-loop",
  "name": "Loop the Loop",
  "formerNames": [],
  "parkId": "atlantic-city",
  "parkName": "Atlantic City",
  "country": "US",
  "countryName": "United States",
  "region": "New Jersey",
  "continent": "North America",
  "heightFt": null,
  "heightM": null,
  "speedMph": null,
  "speedKmh": null,
  "lengthFt": null,
  "lengthM": null,
  "dropFt": null,
  "dropM": null,
  "inversions": 0,
  "gForce": null,
  "duration": null,
  "material": "Steel",
  "type": "Sit-down",
  "propulsion": null,
  "manufacturer": "Edwin Prescott",
  "designer": "Edward A. Green",
  "model": null,
  "status": "closed",
  "yearOpened": 1901,
  "yearClosed": 1912,
  "description": "Loop the Loop (occasionally referred to as the Flip Flap Railway) was a steel, dual-tracked roller coaster located in Atlantic City, New Jersey.  The roller coaster opened in 1901 and operated until 1912.  It was one of the earliest looping roller coasters in the United States.",
  "history": null,
  "notableFeatures": [],
  "records": [],
  "imageUrl": "https://en.wikipedia.org/wiki/Special:FilePath/Looping_the_loop_Atlantic_City_1901.jpg",
  "imageAttribution": null,
  "wikiUrl": "https://en.wikipedia.org/wiki/Loop_the_Loop_(Young's_Pier)",
  "dataSource": [
    "wikipedia"
  ],
  "lastUpdated": "2026-02-28T20:17:11.531Z",
  "dataQuality": "stub",
  "searchTerms": [
    "loop the loop",
    "atlantic city",
    "edwin prescott",
    "sit-down",
    "new jersey"
  ],
  "_meta": {
    "manufacturerMatched": false,
    "manufacturerRaw": "Edwin Prescott"
  },
  "popularityScore": 42.8,
  "popularityTier": "standard",
  "popularityRank": 822
}