{
  "id": "mad-mouse-wonderland",
  "name": "Mad Mouse",
  "formerNames": [],
  "parkId": "wonderland",
  "parkName": "Wonderland",
  "country": "GB",
  "countryName": "United Kingdom",
  "region": null,
  "continent": "Europe",
  "heightFt": null,
  "heightM": null,
  "speedMph": null,
  "speedKmh": null,
  "lengthFt": null,
  "lengthM": null,
  "dropFt": null,
  "dropM": null,
  "inversions": 0,
  "gForce": null,
  "duration": null,
  "material": "Steel",
  "type": "Sit-down",
  "propulsion": null,
  "manufacturer": "Maxwell",
  "designer": null,
  "model": "Wild Mouse",
  "status": "closed",
  "yearOpened": 1975,
  "yearClosed": 1979,
  "description": "Mad Mouse was a hybrid wild mouse roller coaster built by UK manufacturer Maxwell previously located at Wonderland in Cleethorpes, Lincolnshire, England, UK.",
  "history": null,
  "notableFeatures": [],
  "records": [],
  "imageUrl": null,
  "imageAttribution": null,
  "wikiUrl": null,
  "coasterpedia": {
    "url": "https://coasterpedia.net/wiki/Mad_Mouse_(Wonderland_Cleethorpes)",
    "minRiderHeight": null,
    "minUnaccompaniedHeight": null,
    "maxRiderHeight": null,
    "ridersPerTrain": 2,
    "ridersPerHour": null,
    "section": null,
    "subsection": null,
    "steepestDrop": null,
    "cost": null,
    "theme": null,
    "soundtrack": null,
    "serialNumber": null,
    "trainManufacturer": null,
    "trackInversions": null,
    "riderInversions": null,
    "categories": [
      "Wild Mouse",
      "Hybrid"
    ],
    "product": "Wild Mouse",
    "layout": null,
    "bankAngle": null,
    "builder": null,
    "gForce": null,
    "replaced": null,
    "replacement": null,
    "fetchedAt": "2026-02-28T22:08:17.320Z"
  },
  "dataSource": [
    "coasterpedia"
  ],
  "lastUpdated": "2026-02-28T22:08:17.322Z",
  "dataQuality": "stub",
  "searchTerms": [
    "mad mouse",
    "wonderland",
    "maxwell",
    "wild mouse",
    "sit-down"
  ],
  "_meta": {
    "manufacturerMatched": false,
    "manufacturerRaw": "Maxwell"
  },
  "popularityScore": 3.2,
  "popularityTier": "standard",
  "popularityRank": 2789
}