{
  "source": "coasterpedia",
  "articleTitle": "Metropolis",
  "introSection": "Metropolis was a steel roller coaster located at Luna Park in Melbourne, Victoria, Australia. It was dismantled in 2012.",
  "sections": [
    {
      "title": "Colour scheme",
      "content": "First known to have been painted blue with white supports. At some point, the track was repainted red."
    }
  ],
  "fullText": "Metropolis was a steel roller coaster located at Luna Park in Melbourne, Victoria, Australia. It was dismantled in 2012.\n\n\n\nFirst known to have been painted blue with white supports. At some point, the track was repainted red.\n\n\n\n",
  "categories": [
    "Pages_with_short_description",
    "Pages_using_Details_parser_tag",
    "Roller_coasters_by_name",
    "Defunct_roller_coasters",
    "Roller_coasters_in_Australia",
    "Steel_roller_coasters",
    "Roller_coasters_with_a_Zyklon/Galaxi_layout",
    "Pages_with_park_navbox",
    "Roller_coasters_manufactured_by_SDC",
    "Roller_coasters_opened_in_1990",
    "Galaxi_(large)",
    "Roller_coasters_closed_in_2012"
  ],
  "url": "https://coasterpedia.net/wiki/Metropolis",
  "pageId": 12438,
  "fetchedAt": "2026-02-28T22:10:08.318Z",
  "articleLength": 230
}