{
  "source": "coasterpedia",
  "articleTitle": "Mine Coaster",
  "introSection": "Mine Coaster was a steel roller coaster located at Beijing Shijingshan Amusement Park in Shijingshan, Beijing, China.",
  "sections": [],
  "fullText": "Mine Coaster was a steel roller coaster located at Beijing Shijingshan Amusement Park in Shijingshan, Beijing, China.\n\n",
  "categories": [
    "Pages_with_short_description",
    "Pages_using_Details_parser_tag",
    "Roller_coasters_by_name",
    "Defunct_roller_coasters",
    "Roller_coasters_in_China",
    "Steel_roller_coasters",
    "Pages_with_park_navbox",
    "Roller_coasters_manufactured_by_Beijing_Shibaolai_Amusement_Equipment",
    "Roller_coasters_closed_in_2017",
    "Mine_Coaster_(Beijing_Shibaolai_Amusement_Equipment_product)"
  ],
  "url": "https://coasterpedia.net/wiki/Mine_Coaster_(Beijing_Shijingshan_Amusement_Park)",
  "pageId": 72508,
  "fetchedAt": "2026-02-28T22:10:39.655Z",
  "articleLength": 119
}