{
  "source": "coasterpedia",
  "articleTitle": "Roller Coster",
  "introSection": "Roller Coster was a steel kiddie roller coaster previously located at Helensburgh Pier Family Amusement Park in Helensburgh, Argyll and Bute, Scotland, UK. It was owned by the Codona family.\n\nIn the past, the ride had a canvas tunnel which read \"Douglas Codona\". The front of the ride had \"Helensburgh Pier Roller Coster\" printed on it.",
  "sections": [
    {
      "title": "Design",
      "content": "The ride is a Wacky Worm clone."
    }
  ],
  "fullText": "Roller Coster was a steel kiddie roller coaster previously located at Helensburgh Pier Family Amusement Park in Helensburgh, Argyll and Bute, Scotland, UK. It was owned by the Codona family.\n\nIn the past, the ride had a canvas tunnel which read \"Douglas Codona\". The front of the ride had \"Helensburgh Pier Roller Coster\" printed on it.\n\nThe ride is a Wacky Worm clone.\n\n\n\n",
  "categories": [
    "Pages_with_short_description",
    "Pages_using_Details_parser_tag",
    "Roller_coasters_by_name",
    "Defunct_roller_coasters",
    "Roller_coasters_in_the_United_Kingdom",
    "Steel_roller_coasters",
    "Kiddie_roller_coasters",
    "Roller_coasters_with_a_Wacky_Worm_layout",
    "Pages_with_park_navbox",
    "Roller_coasters_manufactured_by_D.P.V._Rides",
    "Brucomela_(D.P.V._Rides_product)",
    "Roller_coasters_opened_in_2004",
    "Roller_coasters_closed_in_2017"
  ],
  "url": "https://coasterpedia.net/wiki/Roller_Coster_(Helensburgh_Pier_Family_Amusement_Park)",
  "pageId": 4675,
  "fetchedAt": "2026-02-28T22:21:52.323Z",
  "articleLength": 373
}