{
  "source": "coasterpedia",
  "articleTitle": "Southern Express",
  "introSection": "Southern Express is a steel kiddie roller coaster located at Tropic Falls in Foley, Alabama, USA.",
  "sections": [
    {
      "title": "History",
      "content": "Southern Express was announced along with Tropic Falls (then called Park at OWA) at the 2016 IAAPA Expo in Orlando, Florida, USA.\n\nThe coaster officially opened on July 21, 2017."
    },
    {
      "title": "Design",
      "content": "The ride has a single helix."
    }
  ],
  "fullText": "Southern Express is a steel kiddie roller coaster located at Tropic Falls in Foley, Alabama, USA.\n\nSouthern Express was announced along with Tropic Falls (then called Park at OWA) at the 2016 IAAPA Expo in Orlando, Florida, USA.\n\nThe coaster officially opened on July 21, 2017.\n\nThe ride has a single helix.\n\n\n\n\n\n",
  "categories": [
    "Pages_with_short_description",
    "Pages_using_Details_parser_tag",
    "Roller_coasters_by_name",
    "Operating_roller_coasters",
    "Roller_coasters_in_Alabama",
    "Steel_roller_coasters",
    "Kiddie_roller_coasters",
    "Roller_coasters_with_a_Single_Helix_Middle_layout",
    "Pages_with_park_navbox",
    "Roller_coasters_manufactured_by_Zamperla",
    "Roller_coasters_opened_in_2017",
    "Family_Gravity_Coaster_80STD"
  ],
  "url": "https://coasterpedia.net/wiki/Southern_Express",
  "pageId": 15971,
  "fetchedAt": "2026-02-28T22:28:01.498Z",
  "articleLength": 313
}