{
  "source": "coasterpedia",
  "articleTitle": "Swing Coaster",
  "introSection": "Swing Coaster is steel side friction roller coaster located at Maharaja World at Coimbatore, Tamil Nadu, India.",
  "sections": [
    {
      "title": "Color scheme",
      "content": "Blue track and black supports."
    }
  ],
  "fullText": "Swing Coaster is steel side friction roller coaster located at Maharaja World at Coimbatore, Tamil Nadu, India.\n\n\n\nBlue track and black supports.\n\n\n\n",
  "categories": [
    "Pages_with_short_description",
    "Pages_using_Details_parser_tag",
    "Infoboxes_using_placeholder_image",
    "Roller_coasters_by_name",
    "Standing_but_not_operating_roller_coasters",
    "Roller_coasters_in_India",
    "Steel_roller_coasters",
    "Side_Friction_roller_coasters",
    "Roller_coasters_with_a_Oval_layout",
    "Pages_with_park_navbox",
    "Roller_coasters_manufactured_by_Madhu_Amusements_&_Leisure_Concepts"
  ],
  "url": "https://coasterpedia.net/wiki/Swing_Coaster",
  "pageId": 50952,
  "fetchedAt": "2026-02-28T22:32:36.219Z",
  "articleLength": 149
}