{
  "id": "wild-mouse-unknown",
  "name": "Wild Mouse",
  "formerNames": [],
  "parkId": "unknown-park",
  "parkName": "Unknown Park",
  "country": "GB",
  "countryName": "United Kingdom",
  "region": null,
  "continent": "Europe",
  "heightFt": 11,
  "heightM": 3.4,
  "speedMph": 45,
  "speedKmh": 72.4,
  "lengthFt": 340,
  "lengthM": 103.6,
  "dropFt": null,
  "dropM": null,
  "inversions": 0,
  "gForce": null,
  "duration": null,
  "material": "Steel",
  "type": "Spinning",
  "propulsion": null,
  "manufacturer": "Reverchon",
  "designer": null,
  "model": "Compact Spinning Coaster",
  "status": "operating",
  "yearOpened": 2002,
  "yearClosed": null,
  "description": "Wild Mouse is a travelling steel spinning wild mouse roller coaster owned by UK fairground operator Danter Attractions.",
  "history": null,
  "notableFeatures": [],
  "records": [],
  "imageUrl": null,
  "imageAttribution": null,
  "wikiUrl": null,
  "coasterpedia": {
    "url": "https://coasterpedia.net/wiki/Wild_Mouse_(Danter_Attractions)",
    "minRiderHeight": null,
    "minUnaccompaniedHeight": null,
    "maxRiderHeight": null,
    "ridersPerTrain": 4,
    "ridersPerHour": null,
    "section": null,
    "subsection": null,
    "steepestDrop": null,
    "cost": null,
    "theme": null,
    "soundtrack": null,
    "serialNumber": null,
    "trainManufacturer": null,
    "trackInversions": null,
    "riderInversions": null,
    "categories": [
      "Steel",
      "Spinning",
      "Wild Mouse"
    ],
    "product": "Compact Spinning Coaster",
    "layout": null,
    "bankAngle": null,
    "builder": null,
    "gForce": null,
    "replaced": null,
    "replacement": null,
    "fetchedAt": "2026-02-28T22:43:14.413Z"
  },
  "dataSource": [
    "coasterpedia"
  ],
  "lastUpdated": "2026-02-28T22:43:14.414Z",
  "dataQuality": "verified",
  "searchTerms": [
    "wild mouse",
    "unknown park",
    "reverchon",
    "compact spinning coaster",
    "spinning"
  ],
  "_meta": {
    "manufacturerMatched": true,
    "manufacturerRaw": "Reverchon"
  },
  "popularityScore": 25.1,
  "popularityTier": "standard",
  "popularityRank": 830
}