{
  "id": "wilko-ak",
  "name": "Wilkołak",
  "formerNames": [],
  "parkId": "majaland-kownaty",
  "parkName": "Majaland Kownaty",
  "country": "PL",
  "countryName": "Poland",
  "region": null,
  "continent": "Europe",
  "heightFt": 72.2,
  "heightM": 22,
  "speedMph": 44.1,
  "speedKmh": 71,
  "lengthFt": 2027.6,
  "lengthM": 618,
  "dropFt": null,
  "dropM": null,
  "inversions": 0,
  "gForce": null,
  "duration": null,
  "material": "Wood",
  "type": "Sit-down",
  "propulsion": null,
  "manufacturer": "Great Coasters International",
  "designer": "Skyline Design",
  "model": null,
  "status": "operating",
  "yearOpened": 2019,
  "yearClosed": null,
  "description": "Wilkołak (Polish for Werewolf) is a wooden roller coaster located at Majaland Kownaty.  It was manufactured by Great Coasters International, designed by Skyline Attractions, and opened on June 29, 2019.  This is the only wooden roller coaster in Poland.",
  "history": null,
  "notableFeatures": [],
  "records": [],
  "imageUrl": null,
  "imageAttribution": null,
  "wikiUrl": null,
  "coasterpedia": {
    "url": "https://coasterpedia.net/wiki/Wilko%C5%82ak",
    "minRiderHeight": null,
    "minUnaccompaniedHeight": null,
    "maxRiderHeight": null,
    "ridersPerTrain": null,
    "ridersPerHour": null,
    "section": null,
    "subsection": null,
    "steepestDrop": null,
    "cost": "€7,500,000",
    "theme": null,
    "soundtrack": null,
    "serialNumber": null,
    "trainManufacturer": null,
    "trackInversions": null,
    "riderInversions": null,
    "categories": [
      "Wooden"
    ],
    "product": null,
    "layout": null,
    "bankAngle": null,
    "builder": null,
    "gForce": null,
    "replaced": null,
    "replacement": null,
    "fetchedAt": "2026-02-28T22:45:17.526Z"
  },
  "dataSource": [
    "coasterpedia"
  ],
  "lastUpdated": "2026-02-28T22:45:17.528Z",
  "dataQuality": "verified",
  "searchTerms": [
    "wilkołak",
    "majaland kownaty",
    "great coasters international",
    "gci",
    "sit-down"
  ],
  "_meta": {
    "manufacturerMatched": true,
    "manufacturerRaw": "Great Coasters International"
  },
  "popularityScore": 15.3,
  "popularityTier": "standard",
  "popularityRank": 1410
}