{
  "source": "coasterpedia",
  "articleTitle": "Wood Express",
  "introSection": "Wood Express is a wooden hybrid roller coaster located at Parc Saint Paul in Saint-Paul, Hauts-de-France, France.",
  "sections": [
    {
      "title": "History",
      "content": "Wood Express was revealed on October 29, 2017. The ride began testing with riders on June 30, 2018. It then officially opened on July 1."
    },
    {
      "title": "Design",
      "content": "Wood Express is a hybrid roller coaster, with wooden track and steel structure."
    }
  ],
  "fullText": "Wood Express is a wooden hybrid roller coaster located at Parc Saint Paul in Saint-Paul, Hauts-de-France, France.\n\nWood Express was revealed on October 29, 2017. The ride began testing with riders on June 30, 2018. It then officially opened on July 1.\n\nWood Express is a hybrid roller coaster, with wooden track and steel structure.\n\n\n\n\n\n",
  "categories": [
    "Pages_with_short_description",
    "Pages_using_Details_parser_tag",
    "Roller_coasters_by_name",
    "Operating_roller_coasters",
    "Roller_coasters_in_France",
    "Wooden_roller_coasters",
    "Hybrid_roller_coasters",
    "Pages_with_park_navbox",
    "Roller_coasters_manufactured_by_The_Gravity_Group,_LLC",
    "Roller_coasters_opened_in_2018",
    "Gravitykraft_Corporation",
    "Hybrid_(Steel_Structure)"
  ],
  "url": "https://coasterpedia.net/wiki/Wood_Express",
  "pageId": 13479,
  "fetchedAt": "2026-02-28T22:45:37.104Z",
  "articleLength": 338
}